django_migrations_auto/__init__.py
django_migrations_auto/asgi.py
django_migrations_auto/settings.py
django_migrations_auto/settings_test.py
django_migrations_auto/tests.py
django_migrations_auto/urls.py
django_migrations_auto/wsgi.py
django_migrations_auto/migrations_log/__init__.py
django_migrations_auto/migrations_log/admin.py
django_migrations_auto/migrations_log/apps.py
django_migrations_auto/migrations_log/models.py
django_migrations_auto/migrations_log/utils.py
django_migrations_auto/migrations_log/views.py
django_migrations_auto/migrations_log/management/__init__.py
django_migrations_auto/migrations_log/management/commands/__init__.py
django_migrations_auto/migrations_log/management/commands/auto_migrate.py
django_migrations_auto/migrations_log/management/commands/makemigrations.py
django_migrations_auto/migrations_log/migrations/0001_initial.py
django_migrations_auto/migrations_log/migrations/__init__.py
django_migrations_auto/test_app/__init__.py
django_migrations_auto/test_app/admin.py
django_migrations_auto/test_app/apps.py
django_migrations_auto/test_app/models.py
django_migrations_auto/test_app/views.py
django_migrations_auto/test_app/migrations/0001_initial.py
django_migrations_auto/test_app/migrations/__init__.py
django_migrations_auto/test_app/scripts/install_sqlite3.sh
django_migrations_auto-0.1.2.dist-info/LICENSE
django_migrations_auto-0.1.2.dist-info/METADATA
django_migrations_auto-0.1.2.dist-info/WHEEL
django_migrations_auto-0.1.2.dist-info/top_level.txt
django_migrations_auto-0.1.2.dist-info/RECORD
